modinit/__init__.py
modinit/__main__.py
modinit/cli.py
modinit/generator.py
modinit/templates/__init__.py
modinit/templates/base/.gitignore
modinit/templates/base/README.md
modinit/templates/base/requirements.txt
modinit/templates/project/main.py
modinit/templates/project/configs/config.yaml
modinit/templates/project/notebooks/prototype.ipynb
modinit/templates/project/src/__init__.py
modinit/templates/project/src/data.py
modinit/templates/project/src/evaluate.py
modinit/templates/project/src/model.py
modinit/templates/project/src/train.py
modinit/templates/project/src/utils.py
modinit/templates/project/tests/__init__.py
modinit/templates/project/tests/test_data.py
modinit/templates/project/tests/test_model.py
modinit/templates/project/tests/test_train.py
modinit/utils/__init__.py
modinit/utils/file_utils.py
modinit-0.1.1.dist-info/licenses/LICENSE
modinit-0.1.1.dist-info/METADATA
modinit-0.1.1.dist-info/WHEEL
modinit-0.1.1.dist-info/entry_points.txt
modinit-0.1.1.dist-info/top_level.txt
modinit-0.1.1.dist-info/RECORD
