Metadata-Version: 2.4
Name: modinit
Version: 0.1.1
Summary: A tool for initializing AI model training repositories
Home-page: https://github.com/eddiegulay/modinit
Author: eddiegulay
Author-email: eddiegulay <edgargulay@outlook.com>
License: MIT
Project-URL: Homepage, https://github.com/eddiegulay/modinit
Project-URL: Bug Tracker, https://github.com/eddiegulay/modinit/issues
Keywords: ai,machine learning,project structure,initialization
Classifier: Programming Language :: Python :: 3
Classifier: License :: OSI Approved :: MIT License
Classifier: Operating System :: OS Independent
Classifier: Development Status :: 4 - Beta
Classifier: Intended Audience :: Developers
Classifier: Intended Audience :: Science/Research
Classifier: Topic :: Scientific/Engineering :: Artificial Intelligence
Requires-Python: >=3.6
License-File: LICENSE
Dynamic: license-file
